{
  "translations": {
    "de": {
      "\nALMANAC (annual calendar)\n ": "\nALMANAC (Jahreskalender)\n ",
      "This module provides calendar information for holidays, school vacations and other calendar dates.": "Dieses Modul bietet Kalenderinformationen für Feiertage, Schulferien und andere Kalenderdaten.",
      "Public holidays ...": "Feiertage ...",
      "Birthdays ...": "Geburtstage ...",
      "School vacations ...": "Schulferien ...",
      "Wedding days ...": "Hochzeitstage ...",
      "Deathdays ...": "Todestage ...",
      "Advanced settings ...": "Erweiterte Einstellungen ...",
      "Country:": "Land:",
      "State:": "Bundesland:",
      "Canton": "Kanton",
      "Schools:": "Schulen:",
      "Dates:": "Termine:",
      "Determine holidays!": "Feiertage ermitteln!",
      "Determine school vacation!": "Schulferien ermitteln!",
      "Determine festive days!": "Festtage ermitteln!",
      "Determine birthdays!": "Geburtstage ermitteln!",
      "Determine wedding days!": "Hochzeitstage ermitteln!",
      "Determine deathdays!": "Todestage ermitteln!",
      "Get information about the current date!": "Informationen zum aktuellen Datum ermitteln!",
      "... to send notification messages to a web front.": "... zum Senden von Nachrichten an ein Webfront.",
      "WebFront Instance:": "WebFront Instanz:",
      "Send notification message:": "Nachricht ans Webfront senden:",
      "Message send time:": "Nachrichten Sendezeit:",
      "Send message to dashboard:": "Meldung an Anzeige senden:",
      "Message life time:": "Lebensdauer der Meldung:",
      "Text message format:": "Format der Textmitteilung:",
      "%Y. birthday of %N (%E)": "%Y. Geburtstag von %N (%E)",
      "%Y. wedding anniversary of %N (%E)": "%Y. Hochzeitstag von %N (%E)",
      "%Y. anniversary of the death of %N (%E)": "%Y. Todestag von %N (%E)",
      "(Specifier: %E = Entry date, %D = Current date, %N = Name, %Y = Year counter)": "(Bezeichner: %E = Eintrittsdatum, %D = Aktuelles Datum, %N = Name, %Y = Jahreszähler)",
      "... to use the dashboard message script. More information you get in the forum to thema: Meldungsanzeige im WebFront.": "... zum Verwenden des Meldungsverwaltungsscripts. Genau Informationen findet man im Forum zum Thema: Meldungsanzeige im WebFront.",
      "Message script:": "Meldungsskript:",
      "Always": "Immer",
      "No": "Nein",
      "Yes": "Ja",
      "Could not load iCal data!": "Konnte iCal Daten nicht laden!",
      "Date": "Datum",
      "Spring": "Frühling",
      "Summer": "Sommer",
      "Fall": "Herbst",
      "Winter": "Winter",
      "Import & export of ...": "Import & Export von ...",
      "Import": "Import",
      "Export": "Export",
      "Import & export birthdays ...": "Import & Export Geburtstage ...",
      "Import & export wedding days ...": "Import & Export Hochzeitstage ...",
      "Import & export death days ...": "Import & Export Todestage ...",
      "File:": "Datei:",
      "birthdays.csv": "geburtstage.csv",
      "weddingdays.csv": "hochzeitstage.csv",
      "deathdays.csv": "todestage.csv",
      "Birthdays": "Geburtstage",
      "Wedding days": "Hochzeitstage",
      "Death days": "Todestage",
      "Date info ...": "Tagesdaten ...",
      "Update": "Aktualisieren",
      "NOTE: No file needs to be selected for export!": "HINWEIS: Für den Export muss keine Datei ausgewählt werden!"
    }
  }
}